test/moore_10110.v
module moore_10110(input clk,reset,input x,output reg y);
parameter s0=0,s1=1,s2=2,s3=3,s4=4,s5=5;
reg [2:0] state,next_state;
always @(posedge clk or posedge reset) begin
if(reset)
state<=s0;
else
state<=next_state;
end
always @(*) begin
case(state)
 s0: next_state = (x) ? s1 : s0;        
        s1: next_state = (x) ? s1 : s2;        
        s2: next_state = (x) ? s3 : s0;        
        s3: next_state = (x) ? s4 : s2;
	s4: next_state = (x) ? s1 : s5;        
        s5: next_state = (x) ? s1 : s0;        
        default: next_state = s0;
endcase
end
always @(*) begin
y = (state==s5) ? 1:0;
end
endmodule

test/moore_10110_tb.v
module moore_10110_tb;
reg clk,reset,x;
wire y;
moore_10110 dut(.clk(clk),.reset(reset),.x(x),.y(y));
always #5 clk=~clk;
initial begin
clk=0;
reset=1;
x=0;
@(posedge clk)
reset=0;
@(posedge clk) x=1;
@(posedge clk) x=0;
@(posedge clk) x=1;
@(posedge clk) x=1;
@(posedge clk) x=0;
@(posedge clk) x=1;
@(posedge clk) x=0;
#20 $finish;
end
initial begin
	$monitor("time=%0t ckl=%b reset=%b x=%b y=%b",$time,clk,reset,x,y);
	$dumpfile("wave.vcd");
	$dumpvars(0);
end
endmodule

test/wave.vcd
$date
	Fri Apr 10 14:05:50 2026
$end
$version
	Icarus Verilog
$end
$timescale
	1s
$end
$scope module moore_10110_tb $end
$var wire 1 ! y $end
$var reg 1 " clk $end
$var reg 1 # reset $end
$var reg 1 $ x $end
$scope module dut $end
$var wire 1 " clk $end
$var wire 1 # reset $end
$var wire 1 $ x $end
$var parameter 32 % s0 $end
$var parameter 32 & s1 $end
$var parameter 32 ' s2 $end
$var parameter 32 ( s3 $end
$var parameter 32 ) s4 $end
$var parameter 32 * s5 $end
$var reg 3 + next_state [2:0] $end
$var reg 3 , state [2:0] $end
$var reg 1 ! y $end
$upscope $end
$upscope $end
$enddefinitions $end
$comment Show the parameter values. $end
$dumpall
b101 *
b100 )
b11 (
b10 '
b1 &
b0 %
$end
#0
$dumpvars
b0 ,
b0 +
0$
1#
0"
0!
$end
#5
0#
1"
#10
0"
#15
b1 +
1$
1"
#20
0"
#25
b1 ,
b10 +
0$
1"
#30
0"
#35
b10 ,
b11 +
1$
1"
#40
0"
#45
b100 +
b11 ,
1"
#50
0"
#55
b100 ,
b101 +
0$
1"
#60
0"
#65
1!
b101 ,
b1 +
1$
1"
#70
0"
#75
0!
b1 ,
b10 +
0$
1"
#80
0"
#85
b0 +
b10 ,
1"
#90
0"
#95
b0 ,
1"
