functions_task/parity_checker.v
module parity_transmitter(input [7:0] data_in,input start,clk,output reg serial_out);
function parity_check(input [7:0] d);
begin
parity_check=^d;
end
endfunction
task send_packet(input [7:0] p_data);
reg p_bit;
integer i;
begin
p_bit=parity_check(p_data);
for(i=0;i<8;i=i+1) begin
@(posedge clk);
serial_out=p_data[i];
end
@(posedge clk);
serial_out=p_bit;
@(posedge clk);
serial_out=1'b1;
end
endtask
initial serial_out=1'b1;
always @(posedge start) begin
send_packet(data_in);
end
endmodule

functions_task/parity_checker_tb.v
module parity_transmitter_tb;
reg clk,start;
reg [7:0] data_in;
wire serial_out;
parity_transmitter dut (.clk(clk),.start(start),.data_in(data_in),.serial_out(serial_out));
always #5 clk=~clk;
initial begin
	clk=0;
	start=0;
	data_in=8'b0;
	#10;
	data_in=8'b00000101;
	#10 start=1;
	#10 start=0;
	#120;
	data_in=8'b00001101;
	#10 start=1;
	#10 start=0;
	#120 $finish;
end
initial begin
	$monitor("time=%0t clk=%b start=%b data_in=%b serial_out=%b",$time,clk,start,data_in,serial_out);
	$dumpfile("wave.vcd");
	$dumpvars(0);
end
endmodule

functions_task/wave,vcd.vcd
$date
	Fri Apr 17 15:34:53 2026
$end
$version
	Icarus Verilog
$end
$timescale
	1s
$end
$scope module parity_transmitter_tb $end
$var wire 1 ! serial_out $end
$var reg 1 " clk $end
$var reg 8 # data_in [7:0] $end
$var reg 1 $ start $end
$scope module dut $end
$var wire 1 " clk $end
$var wire 8 % data_in [7:0] $end
$var wire 1 $ start $end
$var reg 1 ! serial_out $end
$scope function parity_check $end
$var reg 8 & d [7:0] $end
$upscope $end
$scope task send_packet $end
$var reg 1 ' p_bit $end
$var reg 8 ( p_data [7:0] $end
$var integer 32 ) i [31:0] $end
$upscope $end
$upscope $end
$upscope $end
$enddefinitions $end
$comment Show the parameter values. $end
$dumpall
$end
#0
$dumpvars
bx )
bx (
x'
bx &
b0 %
0$
b0 #
0"
1!
$end
#5
1"
#10
0"
b101 #
b101 %
#15
1"
#20
b0 )
0'
b101 &
b101 (
0"
1$
#25
b1 )
1"
#30
0"
0$
#35
b10 )
0!
1"
#40
0"
#45
b11 )
1!
1"
#50
0"
#55
b100 )
0!
1"
#60
0"
#65
b101 )
1"
#70
0"
#75
b110 )
1"
#80
0"
#85
b111 )
1"
#90
0"
#95
b1000 )
1"
#100
0"
#105
1"
#110
0"
#115
1!
1"
#120
0"
#125
1"
#130
0"
#135
1"
#140
0"
#145
1"
#150
0"
b1101 #
b1101 %
#155
1"
#160
b0 )
1'
b1101 &
b1101 (
0"
1$
#165
b1 )
1"
#170
0"
0$
#175
b10 )
0!
1"
#180
0"
#185
b11 )
1!
1"
#190
0"
#195
b100 )
1"
#200
0"
#205
b101 )
0!
1"
#210
0"
#215
b110 )
1"
#220
0"
#225
b111 )
1"
#230
0"
#235
b1000 )
1"
#240
0"
#245
1!
1"
