verilog_assignments/sequence_111000.v
module sequence_111000(input clk,reset,x,output reg y);
parameter s0=0,s1=1,s2=2,s3=3,s4=4,s5=5,s6=6;
reg [2:0] state,next_state;
always @(posedge clk or posedge reset) begin
if(reset)
state<=s0;
else
state<=next_state;
end
always @(*) begin
case(state)
s0 : next_state = (x) ? s1:s4;
s1 : next_state = (x) ? s2:s4;
s2 : next_state = (x) ? s3:s4;
s3 : next_state = (x) ? s3:s4;
s4 : next_state = (x) ? s1:s5;
s5 : next_state = (x) ? s1:s6;
s6 : next_state = (x) ? s1:s6;
endcase
end
always @(*) begin
case(state)
s3,s6 : y=1;
default : y=0;
endcase
end
endmodule

verilog_assignments/sequence_111000_tb.v
module sequence_111000_tb;
reg clk,reset,x;
wire y;
sequence_111000 dut(.clk(clk),.reset(reset),.x(x),.y(y));
always #5 clk=~clk;
initial begin 
	clk=0;
	reset=1;
	x=0;
	#10 reset=0;
	#10 x=1;
	#10 x=1;
	#10 x=1;
	#10 x=1;
#10 x=0;

#10 x=0;
#10 x=0;
#10 x=0;
#10 x=0;

#10 x=1;
#10 x=0;

#20 $finish;
end
initial begin
	$monitor("time=%0t clk=%b reset=%b x=%b y=%b",$time,clk,reset,x,y);
	$dumpfile("wave.vcd");
	$dumpvars(0);
end
endmodule

verilog_assignments/wave.vcd
$date
	Sat Apr 11 09:49:50 2026
$end
$version
	Icarus Verilog
$end
$timescale
	1s
$end
$scope module sequence_111000_tb $end
$var wire 1 ! y $end
$var reg 1 " clk $end
$var reg 1 # reset $end
$var reg 1 $ x $end
$scope module dut $end
$var wire 1 " clk $end
$var wire 1 # reset $end
$var wire 1 $ x $end
$var parameter 32 % s0 $end
$var parameter 32 & s1 $end
$var parameter 32 ' s2 $end
$var parameter 32 ( s3 $end
$var parameter 32 ) s4 $end
$var parameter 32 * s5 $end
$var parameter 32 + s6 $end
$var reg 3 , next_state [2:0] $end
$var reg 3 - state [2:0] $end
$var reg 1 ! y $end
$upscope $end
$upscope $end
$enddefinitions $end
$comment Show the parameter values. $end
$dumpall
b110 +
b101 *
b100 )
b11 (
b10 '
b1 &
b0 %
$end
#0
$dumpvars
b0 -
b100 ,
0$
1#
0"
0!
$end
#5
1"
#10
0"
0#
#15
b101 ,
b100 -
1"
#20
b1 ,
0"
1$
#25
b10 ,
b1 -
1"
#30
0"
#35
b11 ,
b10 -
1"
#40
0"
#45
1!
b11 -
1"
#50
0"
#55
1"
#60
b100 ,
0"
0$
#65
0!
b101 ,
b100 -
1"
#70
0"
#75
b110 ,
b101 -
1"
#80
0"
#85
1!
b110 -
1"
#90
0"
#95
1"
#100
0"
#105
1"
#110
b1 ,
0"
1$
#115
0!
b10 ,
b1 -
1"
#120
b100 ,
0"
0$
#125
b101 ,
b100 -
1"
#130
0"
#135
b110 ,
b101 -
1"
