genvar/ripple_carry_adder/ripple.v
module full_adder(input a,b,cin,output sum,carry);
assign sum=a^b^cin;
assign carry=(a&b)|(cin&(a^b));
endmodule
module ripple_carry#(parameter N=4)
(input [N-1:0] a,b,
	input cin,
output [N-1:0] sum,output cout);
wire [N:0]carry;
assign carry[0]=cin;
genvar i;
generate
for(i=0;i<N;i=i+1) begin : fa_block
full_adder fa(.a(a[i]),.b(b[i]),.cin(carry[i]),.sum(sum[i]),.carry(carry[i+1]));
end
endgenerate
assign cout=carry[N];
endmodule

genvar/ripple_carry_adder/ripple_tb.v
module ripple_tb;
parameter N=4;
reg [N-1:0] a,b;
reg cin;
wire [N-1:0] sum;
wire cout;
ripple_carry #(N) dut(.a(a),.b(b),.cin(cin),.sum(sum),.cout(cout));
integer i;
initial begin
cin=0;
for(i=0;i<16;i=i+1) begin
{a,b}=i;
cin = i%2;
#10;
end
$finish;
end
initial begin
	$monitor("time=%0t a=%b b=%b cin=%b sum=%b cout=%b",$time,a,b,cin,sum,cout);
	$dumpfile("wave.vcd");
	$dumpvars(0);
end
endmodule

genvar/ripple_carry_adder/wave.vcd
$date
	Sat Apr 11 06:12:37 2026
$end
$version
	Icarus Verilog
$end
$timescale
	1s
$end
$scope module ripple_tb $end
$var wire 4 ! sum [3:0] $end
$var wire 1 " cout $end
$var parameter 32 # N $end
$var reg 4 $ a [3:0] $end
$var reg 4 % b [3:0] $end
$var reg 1 & cin $end
$var integer 32 ' i [31:0] $end
$scope module dut $end
$var wire 4 ( a [3:0] $end
$var wire 4 ) b [3:0] $end
$var wire 1 & cin $end
$var wire 4 * sum [3:0] $end
$var wire 1 " cout $end
$var wire 5 + carry [4:0] $end
$var parameter 32 , N $end
$scope begin fa_block[0] $end
$var parameter 2 - i $end
$scope module fa $end
$var wire 1 . a $end
$var wire 1 / b $end
$var wire 1 0 carry $end
$var wire 1 1 cin $end
$var wire 1 2 sum $end
$upscope $end
$upscope $end
$scope begin fa_block[1] $end
$var parameter 2 3 i $end
$scope module fa $end
$var wire 1 4 a $end
$var wire 1 5 b $end
$var wire 1 6 carry $end
$var wire 1 7 cin $end
$var wire 1 8 sum $end
$upscope $end
$upscope $end
$scope begin fa_block[2] $end
$var parameter 3 9 i $end
$scope module fa $end
$var wire 1 : a $end
$var wire 1 ; b $end
$var wire 1 < carry $end
$var wire 1 = cin $end
$var wire 1 > sum $end
$upscope $end
$upscope $end
$scope begin fa_block[3] $end
$var parameter 3 ? i $end
$scope module fa $end
$var wire 1 @ a $end
$var wire 1 A b $end
$var wire 1 B carry $end
$var wire 1 C cin $end
$var wire 1 D sum $end
$upscope $end
$upscope $end
$upscope $end
$upscope $end
$enddefinitions $end
$comment Show the parameter values. $end
$dumpall
b11 ?
b10 9
b1 3
b0 -
b100 ,
b100 #
$end
#0
$dumpvars
0D
0C
0B
0A
0@
0>
0=
0<
0;
0:
08
07
06
05
04
02
01
00
0/
0.
b0 +
b0 *
b0 )
b0 (
b0 '
0&
b0 %
b0 $
0"
b0 !
$end
#10
b10 !
b10 *
18
17
10
11
1/
b11 +
1&
b1 %
b1 )
b1 '
#20
0>
0=
07
06
00
b10 !
b10 *
18
01
0/
15
b0 +
0&
b10 %
b10 )
b10 '
#30
1>
1=
16
b100 !
b100 *
08
17
10
11
1/
b111 +
1&
b11 %
b11 )
b11 '
#40
0D
0=
0C
07
06
0<
00
08
b100 !
b100 *
1>
01
0/
05
1;
b0 +
0&
b100 %
b100 )
b100 '
#50
b110 !
b110 *
18
17
10
11
1/
b11 +
1&
b101 %
b101 )
b101 '
#60
0D
0C
0<
1>
0=
07
06
00
b110 !
b110 *
18
01
0/
15
b0 +
0&
b110 %
b110 )
b110 '
#70
1D
1C
1<
0>
1=
16
b1000 !
b1000 *
08
17
10
11
1/
b1111 +
1&
b111 %
b111 )
b111 '
#80
0=
0C
0"
07
06
0<
0B
00
08
0>
b1000 !
b1000 *
1D
01
0/
05
0;
1A
b0 +
0&
b1000 %
b1000 )
b1000 '
#90
b1010 !
b1010 *
18
17
10
11
1/
b11 +
1&
b1001 %
b1001 )
b1001 '
#100
0>
0=
07
06
00
b1010 !
b1010 *
18
01
0/
15
b0 +
0&
b1010 %
b1010 )
b1010 '
#110
1>
1=
16
b1100 !
b1100 *
08
17
10
11
1/
b111 +
1&
b1011 %
b1011 )
b1011 '
#120
0"
0B
1D
0=
0C
07
06
0<
00
08
b1100 !
b1100 *
1>
01
0/
05
1;
b0 +
0&
b1100 %
b1100 )
b1100 '
#130
b1110 !
b1110 *
18
17
10
11
1/
b11 +
1&
b1101 %
b1101 )
b1101 '
#140
0"
0B
1D
0C
0<
1>
0=
07
06
00
b1110 !
b1110 *
18
01
0/
15
b0 +
0&
b1110 %
b1110 )
b1110 '
#150
1"
1B
0D
1C
1<
0>
1=
16
b0 !
b0 *
08
17
10
11
1/
b11111 +
1&
b1111 %
b1111 )
b1111 '
#160
b10000 '
