fsm/traffic_controller/traffic.v
module traffic(input clk,reset,output reg [2:0] A,output reg [2:0] B);
parameter s0=3'b000,s1=3'b001,s2=3'b010,s3=3'b011;
reg [2:0] state,next_state;
always @(posedge clk or posedge reset) begin
if(reset)
state<=s0;
else
state<=next_state;
end
always @(*) begin
case(state)
s0 : next_state=s1;
s1 : next_state=s2;
s2 : next_state=s3;
s3 : next_state=s0;
default : next_state=s0;
endcase
end
always @(*) begin
case(state)
s0: begin
A=3'b001;
B=3'b100;
end
s1: begin
A=3'b010;
B=3'b100;
end
s2: begin
A=3'b100;
B=3'b001;
end
s3: begin
A=3'b100;
B=3'b010;
end
endcase
end
endmodule

fsm/traffic_controller/traffic_tb.v
module traffic_tb;
reg clk,reset;
wire [2:0] A;
wire [2:0] B;
traffic dut(.clk(clk),.reset(reset),.A(A),.B(B));
always #5 clk=~clk;
initial begin
clk=0;
reset=1;
#10 reset=0;
#100 $finish;
end
initial begin
$dumpfile("wave.vcd");
$dumpvars(0);
$monitor("time=%0t clk=%b reset=%b A=%b B=%b",$time,clk,reset,A,B);
end
endmodule

fsm/traffic_controller/wave.vcd
$date
	Thu Apr  9 11:48:38 2026
$end
$version
	Icarus Verilog
$end
$timescale
	1s
$end
$scope module traffic_tb $end
$var wire 3 ! B [2:0] $end
$var wire 3 " A [2:0] $end
$var reg 1 # clk $end
$var reg 1 $ reset $end
$scope module dut $end
$var wire 1 # clk $end
$var wire 1 $ reset $end
$var parameter 3 % s0 $end
$var parameter 3 & s1 $end
$var parameter 3 ' s2 $end
$var parameter 3 ( s3 $end
$var reg 3 ) A [2:0] $end
$var reg 3 * B [2:0] $end
$var reg 3 + next_state [2:0] $end
$var reg 3 , state [2:0] $end
$upscope $end
$upscope $end
$enddefinitions $end
$comment Show the parameter values. $end
$dumpall
b11 (
b10 '
b1 &
b0 %
$end
#0
$dumpvars
b0 ,
b1 +
b100 *
b1 )
1$
0#
b1 "
b100 !
$end
#5
1#
#10
0#
0$
#15
b10 +
b10 "
b10 )
b1 ,
1#
#20
0#
#25
b1 !
b1 *
b100 "
b100 )
b11 +
b10 ,
1#
#30
0#
#35
b0 +
b10 !
b10 *
b11 ,
1#
#40
0#
#45
b100 !
b100 *
b1 "
b1 )
b1 +
b0 ,
1#
#50
0#
#55
b10 +
b10 "
b10 )
b1 ,
1#
#60
0#
#65
b1 !
b1 *
b100 "
b100 )
b11 +
b10 ,
1#
#70
0#
#75
b0 +
b10 !
b10 *
b11 ,
1#
#80
0#
#85
b100 !
b100 *
b1 "
b1 )
b1 +
b0 ,
1#
#90
0#
#95
b10 +
b10 "
b10 )
b1 ,
1#
#100
0#
#105
b1 !
b1 *
b100 "
b100 )
b11 +
b10 ,
1#
