fsm/vending_mealy.v/vending_mealy.v
module vending_mealy(input clk,reset,input [1:0] coin,output reg dispense,change);
parameter s0=2'b00,s1=2'b01;
reg [1:0] state,next_state;
always @(posedge clk or posedge reset) begin
if(reset)
	state<=s0;
else
	state<=next_state;
end
always @(*) begin
	dispense=0;
	change=0;
	next_state=state;
	case(state)
		s0: begin
			if(coin == 2'b01)
				next_state=s1;
			else if(coin == 2'b10) begin
				dispense=1;
			        next_state=s0;
		end
	end
		s1: begin
			if(coin == 2'b01) begin
				dispense=1;
			        next_state=s0;
				end else if(coin == 2'b10) begin
				dispense=1;
			        change=1;
			        next_state=s0;
		end
	end
endcase
end
endmodule

fsm/vending_mealy.v/vending_mealy_tb.v
module vending_mealy_tb;
reg clk,reset;
reg [1:0] coin;
wire dispense,change;
vending_mealy dut(.clk(clk),.reset(reset),.coin(coin),.dispense(dispense),.change(change));
always #5 clk=~clk;
initial begin
clk=0;
reset=1;
coin=2'b00;
 #12 reset = 0; 

    @(posedge clk);
    coin = 2'b01;

    @(posedge clk);
    coin = 2'b01;
    @(posedge clk);
    coin = 2'b00;

    @(posedge clk);
    coin = 2'b10;
    @(posedge clk);
    coin =2'b00;

    @(posedge clk);
    coin = 2'b01;

    @(posedge clk);
    coin = 2'b10;
    @(posedge clk);
    coin = 2'b00;

    #20 $finish;
end
initial begin
$dumpfile("wave.vcd");
$dumpvars(0);
$monitor("time=%0t clk=%b reset=%b coin=%b dispense=%b change=%b state=%b next_state=%b",$time,clk,reset,coin,dispense,change,dut.state,dut.next_state);
end
endmodule

fsm/vending_mealy.v/wave.vcd
$date
	Thu Apr  9 15:03:40 2026
$end
$version
	Icarus Verilog
$end
$timescale
	1s
$end
$scope module vending_mealy_tb $end
$var wire 1 ! dispense $end
$var wire 1 " change $end
$var reg 1 # clk $end
$var reg 2 $ coin [1:0] $end
$var reg 1 % reset $end
$scope module dut $end
$var wire 1 # clk $end
$var wire 2 & coin [1:0] $end
$var wire 1 % reset $end
$var parameter 2 ' s0 $end
$var parameter 2 ( s1 $end
$var reg 1 " change $end
$var reg 1 ! dispense $end
$var reg 2 ) next_state [1:0] $end
$var reg 2 * state [1:0] $end
$upscope $end
$upscope $end
$enddefinitions $end
$comment Show the parameter values. $end
$dumpall
b1 (
b0 '
$end
#0
$dumpvars
b0 *
b0 )
b0 &
1%
b0 $
0#
0"
0!
$end
#5
1#
#10
0#
#12
0%
#15
b1 )
b1 $
b1 &
1#
#20
0#
#25
b0 )
1!
b1 *
1#
#30
0#
#35
b0 *
b0 )
0!
b0 $
b0 &
1#
#40
0#
#45
1!
b10 $
b10 &
1#
#50
0#
#55
0!
b0 $
b0 &
1#
#60
0#
#65
b1 )
b1 $
b1 &
1#
#70
0#
#75
1"
b1 *
1!
b0 )
b10 $
b10 &
1#
#80
0#
#85
b0 *
b0 )
0"
0!
b0 $
b0 &
1#
